{
 "recipeName": "must-have-dashes-instead-of-spaces",
 "data": {
  "cookTime": "",
  "difficulty": "",
  "prepTime": ""
 },
 "description": [
  "",
  "",
  ""
 ],
 "furtherInfo": [
  "",
  ""
 ],
 "image": "",
 "ingredients": [
  {
   "sectionItems": [
    {
     "amount": "",
     "ingredient": "",
     "unit": ""
    },
    {
     "amount": "",
     "ingredient": "",
     "unit": ""
    }
   ],
   "sectionName": ""
  },
  {
   "sectionItems": [
    {
     "amount": "",
     "ingredient": "",
     "unit": ""
    },
    {
     "amount": "",
     "ingredient": "",
     "unit": ""
    },
    {
     "amount": "",
     "ingredient": "",
     "unit": ""
    }
   ],
   "sectionName": ""
  }
 ],
 "shortDescription": "",
 "stepsDetailed": [
  {
   "sectionName": "",
   "sectionItems": [
    "",
    "",
    "",
    ""
   ]
  },
  {
   "sectionName": "",
   "sectionItems": [
    "",
    "",
    "",
    ""
   ]
  }
 ],
 "method": [
  {
   "sectionName": "",
   "sectionItems": [
    "",
    "",
    "",
    ""
   ]
  },
  {
   "sectionName": "",
   "sectionItems": [
    "",
    "",
    "",
    ""
   ]
  }
 ],
 "tags": [
  ""
 ],
 "title": "can have space. is CaSe SenSiTivE"
}

This is JSON, NOT a js object, remmeber to use the correct syntax.
¬